{
    "hi" : "Bagaimana saya bisa bantu anda hari ini?",
    "halo" : "halo juga",
    "kamu siapa" : "saya maxbot",
    "nama mu siapa" : "namaku maxbot,saya dikembangkan oleh tim bima slengekan_production",
    "buka youtube" : "membuka youtube",
    "buka facebook" : "membuka facebook",
    "buka google" : "membuka google",
    "buka instagram" : "membuka instagram",
    "siapa pembuatmu" : "saya dikembangkan oleh tim bima slengekan_production",
    "tanggal berapa anda dibuat" : "31 oktober",
    "tahun berapa anda dibuat" : "2023",
    "tidak perlu" : "ok jika ada pertanyaan atau apapun silahkan saja"
}